LICENSE
MANIFEST.in
README.rst
pyproject.toml
setup.cfg
setup.py
elasticapm/__init__.py
elasticapm/base.py
elasticapm/events.py
elasticapm/middleware.py
elasticapm/processors.py
elasticapm/traces.py
elasticapm/version.py
elasticapm/conf/__init__.py
elasticapm/conf/constants.py
elasticapm/context/__init__.py
elasticapm/context/base.py
elasticapm/context/contextvars.py
elasticapm/context/threadlocal.py
elasticapm/contrib/__init__.py
elasticapm/contrib/asgi.py
elasticapm/contrib/paste.py
elasticapm/contrib/aiohttp/__init__.py
elasticapm/contrib/aiohttp/middleware.py
elasticapm/contrib/aiohttp/utils.py
elasticapm/contrib/asyncio/__init__.py
elasticapm/contrib/asyncio/traces.py
elasticapm/contrib/celery/__init__.py
elasticapm/contrib/django/__init__.py
elasticapm/contrib/django/apps.py
elasticapm/contrib/django/client.py
elasticapm/contrib/django/context_processors.py
elasticapm/contrib/django/handlers.py
elasticapm/contrib/django/utils.py
elasticapm/contrib/django/celery/__init__.py
elasticapm/contrib/django/celery/models.py
elasticapm/contrib/django/management/__init__.py
elasticapm/contrib/django/management/commands/__init__.py
elasticapm/contrib/django/management/commands/elasticapm.py
elasticapm/contrib/django/middleware/__init__.py
elasticapm/contrib/django/middleware/wsgi.py
elasticapm/contrib/flask/__init__.py
elasticapm/contrib/flask/utils.py
elasticapm/contrib/grpc/__init__.py
elasticapm/contrib/grpc/client_interceptor.py
elasticapm/contrib/grpc/server_interceptor.py
elasticapm/contrib/grpc/utils.py
elasticapm/contrib/opentelemetry/__init__.py
elasticapm/contrib/opentelemetry/context.py
elasticapm/contrib/opentelemetry/span.py
elasticapm/contrib/opentelemetry/trace.py
elasticapm/contrib/opentelemetry/utils.py
elasticapm/contrib/opentracing/__init__.py
elasticapm/contrib/opentracing/span.py
elasticapm/contrib/opentracing/tracer.py
elasticapm/contrib/pylons/__init__.py
elasticapm/contrib/rq/__init__.py
elasticapm/contrib/sanic/__init__.py
sf_elastic_apm.egg-info/PKG-INFO
sf_elastic_apm.egg-info/SOURCES.txt
sf_elastic_apm.egg-info/dependency_links.txt
sf_elastic_apm.egg-info/not-zip-safe
sf_elastic_apm.egg-info/requires.txt
sf_elastic_apm.egg-info/top_level.txt