Metadata-Version: 2.1
Name: sf-elastic-apm
Version: 6.13.2
Summary: The official Python module for Elastic APM
Home-page: https://github.com/snappyflow/sftrace-python-agent
Author: Elastic, Inc
License: BSD
Project-URL: Documentation, https://www.elastic.co/guide/en/apm/agent/python/current/index.html
Project-URL: Release notes, https://www.elastic.co/guide/en/apm/agent/python/current/release-notes.html
Project-URL: Source, https://github.com/elastic/apm-agent-python
Project-URL: Tracker, https://github.com/elastic/apm-agent-python/issues
Classifier: Intended Audience :: Developers
Classifier: Intended Audience :: System Administrators
Classifier: Operating System :: OS Independent
Classifier: Topic :: Software Development
Classifier: Programming Language :: Python
Classifier: Programming Language :: Python :: 3.6
Classifier: Programming Language :: Python :: 3.7
Classifier: Programming Language :: Python :: 3.8
Classifier: Programming Language :: Python :: 3.9
Classifier: Programming Language :: Python :: 3.10
Classifier: Programming Language :: Python :: 3.11
Classifier: Programming Language :: Python :: Implementation :: CPython
Classifier: Programming Language :: Python :: Implementation :: PyPy
Classifier: License :: OSI Approved :: BSD License
Requires-Python: <4,>=3.6
Provides-Extra: flask
Provides-Extra: aiohttp
Provides-Extra: tornado
Provides-Extra: starlette
Provides-Extra: opentracing
Provides-Extra: sanic
Provides-Extra: opentelemetry
License-File: LICENSE
